{
  "id": "Christian Carion",
  "type": "person",
  "slug": "christian-carion",
  "name": "Christian Carion",
  "birthYear": 1963,
  "nationality": "FR",
  "gender": "M",
  "director": [
    {
      "id": "FR2022_131",
      "slug": "fr2022-131-une-belle-course",
      "title": {
        "native": "Une belle course",
        "english": "Driving Madeleine"
      },
      "filmType": "F",
      "genre": "COM",
      "release": {
        "type": "THE",
        "year": 2022
      },
      "tags": "cross-gender friendship",
      "production": {
        "country": "FR",
        "share": "MAJ"
      }
    },
    {
      "id": "FR2022_131",
      "slug": "fr2022-131-une-belle-course",
      "title": {
        "native": "Une belle course",
        "english": "Driving Madeleine"
      },
      "filmType": "F",
      "genre": "DRA",
      "release": {
        "type": "THE",
        "year": 2022
      },
      "tags": "personal memory",
      "production": {
        "country": "FR",
        "share": "MAJ"
      }
    },
    {
      "id": "FR2022_131",
      "slug": "fr2022-131-une-belle-course",
      "title": {
        "native": "Une belle course",
        "english": "Driving Madeleine"
      },
      "filmType": "F",
      "genre": "DRA",
      "release": {
        "type": "THE",
        "year": 2022
      },
      "tags": "widowhood",
      "production": {
        "country": "BE",
        "share": "MIN"
      }
    },
    {
      "id": "FR2022_131",
      "slug": "fr2022-131-une-belle-course",
      "title": {
        "native": "Une belle course",
        "english": "Driving Madeleine"
      },
      "filmType": "F",
      "genre": "COM",
      "release": {
        "type": "THE",
        "year": 2022
      },
      "tags": "urban",
      "production": {
        "country": "FR",
        "share": "MAJ"
      }
    },
    {
      "id": "FR2022_131",
      "slug": "fr2022-131-une-belle-course",
      "title": {
        "native": "Une belle course",
        "english": "Driving Madeleine"
      },
      "filmType": "F",
      "genre": "COM",
      "release": {
        "type": "THE",
        "year": 2022
      },
      "tags": "widowhood",
      "production": {
        "country": "BE",
        "share": "MIN"
      }
    },
    {
      "id": "FR2022_131",
      "slug": "fr2022-131-une-belle-course",
      "title": {
        "native": "Une belle course",
        "english": "Driving Madeleine"
      },
      "filmType": "F",
      "genre": "DRA",
      "release": {
        "type": "THE",
        "year": 2022
      },
      "tags": "stages of life",
      "production": {
        "country": "FR",
        "share": "MAJ"
      }
    },
    {
      "id": "FR2021_099",
      "slug": "fr2021-099-my-son",
      "title": {
        "native": "My Son",
        "english": "My Son"
      },
      "filmType": "F",
      "genre": "THR",
      "release": {
        "type": "THE",
        "year": 2021
      },
      "tags": "high rank employment",
      "production": {
        "country": "GB",
        "share": "MIN"
      }
    },
    {
      "id": "FR2022_131",
      "slug": "fr2022-131-une-belle-course",
      "title": {
        "native": "Une belle course",
        "english": "Driving Madeleine"
      },
      "filmType": "F",
      "genre": "DRA",
      "release": {
        "type": "THE",
        "year": 2022
      },
      "tags": "intergenerational friendship",
      "production": {
        "country": "BE",
        "share": "MIN"
      }
    },
    {
      "id": "FR2022_131",
      "slug": "fr2022-131-une-belle-course",
      "title": {
        "native": "Une belle course",
        "english": "Driving Madeleine"
      },
      "filmType": "F",
      "genre": "COM",
      "release": {
        "type": "THE",
        "year": 2022
      },
      "tags": "retirement",
      "production": {
        "country": "BE",
        "share": "MIN"
      }
    },
    {
      "id": "FR2021_099",
      "slug": "fr2021-099-my-son",
      "title": {
        "native": "My Son",
        "english": "My Son"
      },
      "filmType": "F",
      "genre": "DRA",
      "release": {
        "type": "THE",
        "year": 2021
      },
      "tags": "state institutions",
      "production": {
        "country": "GB",
        "share": "MIN"
      }
    },
    {
      "id": "FR2021_099",
      "slug": "fr2021-099-my-son",
      "title": {
        "native": "My Son",
        "english": "My Son"
      },
      "filmType": "F",
      "genre": "DRA",
      "release": {
        "type": "THE",
        "year": 2021
      },
      "tags": "state institutions",
      "production": {
        "country": "DE",
        "share": "MIN"
      }
    },
    {
      "id": "FR2022_131",
      "slug": "fr2022-131-une-belle-course",
      "title": {
        "native": "Une belle course",
        "english": "Driving Madeleine"
      },
      "filmType": "F",
      "genre": "DRA",
      "release": {
        "type": "THE",
        "year": 2022
      },
      "tags": "intergenerational friendship",
      "production": {
        "country": "FR",
        "share": "MAJ"
      }
    },
    {
      "id": "FR2022_131",
      "slug": "fr2022-131-une-belle-course",
      "title": {
        "native": "Une belle course",
        "english": "Driving Madeleine"
      },
      "filmType": "F",
      "genre": "COM",
      "release": {
        "type": "THE",
        "year": 2022
      },
      "tags": "intergenerational friendship",
      "production": {
        "country": "BE",
        "share": "MIN"
      }
    },
    {
      "id": "FR2022_131",
      "slug": "fr2022-131-une-belle-course",
      "title": {
        "native": "Une belle course",
        "english": "Driving Madeleine"
      },
      "filmType": "F",
      "genre": "DRA",
      "release": {
        "type": "THE",
        "year": 2022
      },
      "tags": "urban",
      "production": {
        "country": "BE",
        "share": "MIN"
      }
    },
    {
      "id": "FR2022_131",
      "slug": "fr2022-131-une-belle-course",
      "title": {
        "native": "Une belle course",
        "english": "Driving Madeleine"
      },
      "filmType": "F",
      "genre": "COM",
      "release": {
        "type": "THE",
        "year": 2022
      },
      "tags": "widowhood",
      "production": {
        "country": "FR",
        "share": "MAJ"
      }
    },
    {
      "id": "FR2022_131",
      "slug": "fr2022-131-une-belle-course",
      "title": {
        "native": "Une belle course",
        "english": "Driving Madeleine"
      },
      "filmType": "F",
      "genre": "COM",
      "release": {
        "type": "THE",
        "year": 2022
      },
      "tags": "cross-gender friendship",
      "production": {
        "country": "BE",
        "share": "MIN"
      }
    },
    {
      "id": "FR2021_099",
      "slug": "fr2021-099-my-son",
      "title": {
        "native": "My Son",
        "english": "My Son"
      },
      "filmType": "F",
      "genre": "DRA",
      "release": {
        "type": "THE",
        "year": 2021
      },
      "tags": "high rank employment",
      "production": {
        "country": "FR",
        "share": "MAJ"
      }
    },
    {
      "id": "FR2021_099",
      "slug": "fr2021-099-my-son",
      "title": {
        "native": "My Son",
        "english": "My Son"
      },
      "filmType": "F",
      "genre": "THR",
      "release": {
        "type": "THE",
        "year": 2021
      },
      "tags": "high rank employment",
      "production": {
        "country": "DE",
        "share": "MIN"
      }
    },
    {
      "id": "FR2021_099",
      "slug": "fr2021-099-my-son",
      "title": {
        "native": "My Son",
        "english": "My Son"
      },
      "filmType": "F",
      "genre": "THR",
      "release": {
        "type": "THE",
        "year": 2021
      },
      "tags": "state institutions",
      "production": {
        "country": "GB",
        "share": "MIN"
      }
    },
    {
      "id": "FR2022_131",
      "slug": "fr2022-131-une-belle-course",
      "title": {
        "native": "Une belle course",
        "english": "Driving Madeleine"
      },
      "filmType": "F",
      "genre": "DRA",
      "release": {
        "type": "THE",
        "year": 2022
      },
      "tags": "retirement home",
      "production": {
        "country": "BE",
        "share": "MIN"
      }
    },
    {
      "id": "FR2021_099",
      "slug": "fr2021-099-my-son",
      "title": {
        "native": "My Son",
        "english": "My Son"
      },
      "filmType": "F",
      "genre": "DRA",
      "release": {
        "type": "THE",
        "year": 2021
      },
      "tags": "high rank employment",
      "production": {
        "country": "DE",
        "share": "MIN"
      }
    },
    {
      "id": "FR2022_131",
      "slug": "fr2022-131-une-belle-course",
      "title": {
        "native": "Une belle course",
        "english": "Driving Madeleine"
      },
      "filmType": "F",
      "genre": "COM",
      "release": {
        "type": "THE",
        "year": 2022
      },
      "tags": "retirement home",
      "production": {
        "country": "BE",
        "share": "MIN"
      }
    },
    {
      "id": "FR2022_131",
      "slug": "fr2022-131-une-belle-course",
      "title": {
        "native": "Une belle course",
        "english": "Driving Madeleine"
      },
      "filmType": "F",
      "genre": "DRA",
      "release": {
        "type": "THE",
        "year": 2022
      },
      "tags": "stages of life",
      "production": {
        "country": "BE",
        "share": "MIN"
      }
    },
    {
      "id": "FR2021_099",
      "slug": "fr2021-099-my-son",
      "title": {
        "native": "My Son",
        "english": "My Son"
      },
      "filmType": "F",
      "genre": "THR",
      "release": {
        "type": "THE",
        "year": 2021
      },
      "tags": "state institutions",
      "production": {
        "country": "FR",
        "share": "MAJ"
      }
    },
    {
      "id": "FR2021_099",
      "slug": "fr2021-099-my-son",
      "title": {
        "native": "My Son",
        "english": "My Son"
      },
      "filmType": "F",
      "genre": "THR",
      "release": {
        "type": "THE",
        "year": 2021
      },
      "tags": "high rank employment",
      "production": {
        "country": "FR",
        "share": "MAJ"
      }
    },
    {
      "id": "FR2022_131",
      "slug": "fr2022-131-une-belle-course",
      "title": {
        "native": "Une belle course",
        "english": "Driving Madeleine"
      },
      "filmType": "F",
      "genre": "COM",
      "release": {
        "type": "THE",
        "year": 2022
      },
      "tags": "retirement",
      "production": {
        "country": "FR",
        "share": "MAJ"
      }
    },
    {
      "id": "FR2021_099",
      "slug": "fr2021-099-my-son",
      "title": {
        "native": "My Son",
        "english": "My Son"
      },
      "filmType": "F",
      "genre": "DRA",
      "release": {
        "type": "THE",
        "year": 2021
      },
      "tags": "high rank employment",
      "production": {
        "country": "GB",
        "share": "MIN"
      }
    },
    {
      "id": "FR2021_099",
      "slug": "fr2021-099-my-son",
      "title": {
        "native": "My Son",
        "english": "My Son"
      },
      "filmType": "F",
      "genre": "DRA",
      "release": {
        "type": "THE",
        "year": 2021
      },
      "tags": "state institutions",
      "production": {
        "country": "FR",
        "share": "MAJ"
      }
    },
    {
      "id": "FR2022_131",
      "slug": "fr2022-131-une-belle-course",
      "title": {
        "native": "Une belle course",
        "english": "Driving Madeleine"
      },
      "filmType": "F",
      "genre": "COM",
      "release": {
        "type": "THE",
        "year": 2022
      },
      "tags": "intergenerational friendship",
      "production": {
        "country": "FR",
        "share": "MAJ"
      }
    },
    {
      "id": "FR2022_131",
      "slug": "fr2022-131-une-belle-course",
      "title": {
        "native": "Une belle course",
        "english": "Driving Madeleine"
      },
      "filmType": "F",
      "genre": "DRA",
      "release": {
        "type": "THE",
        "year": 2022
      },
      "tags": "cross-gender friendship",
      "production": {
        "country": "FR",
        "share": "MAJ"
      }
    },
    {
      "id": "FR2022_131",
      "slug": "fr2022-131-une-belle-course",
      "title": {
        "native": "Une belle course",
        "english": "Driving Madeleine"
      },
      "filmType": "F",
      "genre": "DRA",
      "release": {
        "type": "THE",
        "year": 2022
      },
      "tags": "personal memory",
      "production": {
        "country": "BE",
        "share": "MIN"
      }
    },
    {
      "id": "FR2022_131",
      "slug": "fr2022-131-une-belle-course",
      "title": {
        "native": "Une belle course",
        "english": "Driving Madeleine"
      },
      "filmType": "F",
      "genre": "DRA",
      "release": {
        "type": "THE",
        "year": 2022
      },
      "tags": "widowhood",
      "production": {
        "country": "FR",
        "share": "MAJ"
      }
    },
    {
      "id": "FR2021_099",
      "slug": "fr2021-099-my-son",
      "title": {
        "native": "My Son",
        "english": "My Son"
      },
      "filmType": "F",
      "genre": "THR",
      "release": {
        "type": "THE",
        "year": 2021
      },
      "tags": "state institutions",
      "production": {
        "country": "DE",
        "share": "MIN"
      }
    },
    {
      "id": "FR2022_131",
      "slug": "fr2022-131-une-belle-course",
      "title": {
        "native": "Une belle course",
        "english": "Driving Madeleine"
      },
      "filmType": "F",
      "genre": "DRA",
      "release": {
        "type": "THE",
        "year": 2022
      },
      "tags": "urban",
      "production": {
        "country": "FR",
        "share": "MAJ"
      }
    },
    {
      "id": "FR2022_131",
      "slug": "fr2022-131-une-belle-course",
      "title": {
        "native": "Une belle course",
        "english": "Driving Madeleine"
      },
      "filmType": "F",
      "genre": "DRA",
      "release": {
        "type": "THE",
        "year": 2022
      },
      "tags": "retirement",
      "production": {
        "country": "BE",
        "share": "MIN"
      }
    },
    {
      "id": "FR2022_131",
      "slug": "fr2022-131-une-belle-course",
      "title": {
        "native": "Une belle course",
        "english": "Driving Madeleine"
      },
      "filmType": "F",
      "genre": "COM",
      "release": {
        "type": "THE",
        "year": 2022
      },
      "tags": "stages of life",
      "production": {
        "country": "BE",
        "share": "MIN"
      }
    },
    {
      "id": "FR2022_131",
      "slug": "fr2022-131-une-belle-course",
      "title": {
        "native": "Une belle course",
        "english": "Driving Madeleine"
      },
      "filmType": "F",
      "genre": "COM",
      "release": {
        "type": "THE",
        "year": 2022
      },
      "tags": "personal memory",
      "production": {
        "country": "BE",
        "share": "MIN"
      }
    },
    {
      "id": "FR2022_131",
      "slug": "fr2022-131-une-belle-course",
      "title": {
        "native": "Une belle course",
        "english": "Driving Madeleine"
      },
      "filmType": "F",
      "genre": "DRA",
      "release": {
        "type": "THE",
        "year": 2022
      },
      "tags": "cross-gender friendship",
      "production": {
        "country": "BE",
        "share": "MIN"
      }
    },
    {
      "id": "FR2022_131",
      "slug": "fr2022-131-une-belle-course",
      "title": {
        "native": "Une belle course",
        "english": "Driving Madeleine"
      },
      "filmType": "F",
      "genre": "DRA",
      "release": {
        "type": "THE",
        "year": 2022
      },
      "tags": "retirement",
      "production": {
        "country": "FR",
        "share": "MAJ"
      }
    },
    {
      "id": "FR2022_131",
      "slug": "fr2022-131-une-belle-course",
      "title": {
        "native": "Une belle course",
        "english": "Driving Madeleine"
      },
      "filmType": "F",
      "genre": "COM",
      "release": {
        "type": "THE",
        "year": 2022
      },
      "tags": "retirement home",
      "production": {
        "country": "FR",
        "share": "MAJ"
      }
    },
    {
      "id": "FR2022_131",
      "slug": "fr2022-131-une-belle-course",
      "title": {
        "native": "Une belle course",
        "english": "Driving Madeleine"
      },
      "filmType": "F",
      "genre": "COM",
      "release": {
        "type": "THE",
        "year": 2022
      },
      "tags": "urban",
      "production": {
        "country": "BE",
        "share": "MIN"
      }
    },
    {
      "id": "FR2022_131",
      "slug": "fr2022-131-une-belle-course",
      "title": {
        "native": "Une belle course",
        "english": "Driving Madeleine"
      },
      "filmType": "F",
      "genre": "COM",
      "release": {
        "type": "THE",
        "year": 2022
      },
      "tags": "personal memory",
      "production": {
        "country": "FR",
        "share": "MAJ"
      }
    },
    {
      "id": "FR2022_131",
      "slug": "fr2022-131-une-belle-course",
      "title": {
        "native": "Une belle course",
        "english": "Driving Madeleine"
      },
      "filmType": "F",
      "genre": "COM",
      "release": {
        "type": "THE",
        "year": 2022
      },
      "tags": "stages of life",
      "production": {
        "country": "FR",
        "share": "MAJ"
      }
    },
    {
      "id": "FR2022_131",
      "slug": "fr2022-131-une-belle-course",
      "title": {
        "native": "Une belle course",
        "english": "Driving Madeleine"
      },
      "filmType": "F",
      "genre": "DRA",
      "release": {
        "type": "THE",
        "year": 2022
      },
      "tags": "retirement home",
      "production": {
        "country": "FR",
        "share": "MAJ"
      }
    }
  ]
}