{
  "person_id":"Florian Zeller",
  "person_name":"Florian Zeller",
  "birth_year":1979,
  "death_year":0,
  "gender":"M",
  "person_nat":"FR",
  "id":"GB2021_005",
  "director":"Florian Zeller",
  "filmType":"F",
  "type":"film",
  "slug":"gb2021-005-the-father",
  "title":{
    "native":"The Father",
    "english":""
  },
  "release":{
    "type":"THE",
    "date":1636156800000,
    "year":2021
  },
  "genre":"HOR",
  "tags":"daily routine",
  "media":{
    "trailerUrl":"https:\/\/www.youtube.com\/watch?v=OFnoRaLAclg",
    "posterUrl":"https:\/\/www.imdb.com\/title\/tt10272386\/mediaviewer\/rm525706753\/?ref_=tt_ov_i"
  },
  "synopsis":{
    "native":"A man refuses all assistance from his daughter as he ages. As he tries to make sense of his changing circumstances, he begins to doubt his loved ones, his own mind and even the fabric of his reality.",
    "english":null
  },
  "production":{
    "country":"FR",
    "share":"MIN"
  },
  "directed":{
    "id":"GB2021_005",
    "slug":"gb2021-005-the-father",
    "title":{
      "native":"The Father",
      "english":""
    },
    "filmType":"F",
    "genre":"HOR",
    "release":{
      "type":"THE",
      "date":1636156800000,
      "year":2021
    },
    "tags":"daily routine",
    "media":{
      "trailerUrl":"https:\/\/www.youtube.com\/watch?v=OFnoRaLAclg",
      "posterUrl":"https:\/\/www.imdb.com\/title\/tt10272386\/mediaviewer\/rm525706753\/?ref_=tt_ov_i"
    },
    "synopsis":{
      "native":"A man refuses all assistance from his daughter as he ages. As he tries to make sense of his changing circumstances, he begins to doubt his loved ones, his own mind and even the fabric of his reality.",
      "english":null
    },
    "production":{
      "country":"FR",
      "share":"MIN"
    }
  }
}