{
  "id": "Jean-Pierre Pozzi",
  "type": "person",
  "slug": "jean-pierre-pozzi",
  "name": "Jean-Pierre Pozzi",
  "nationality": "FR",
  "gender": "M",
  "director": [
    {
      "id": "FR2022_027",
      "slug": "fr2022-027-ps-la-dipsarition",
      "title": {
        "native": "PS : La diPSarition ?"
      },
      "filmType": "D",
      "genre": "DEX",
      "release": {
        "type": "THE",
        "year": 2022
      },
      "tags": "professional politics",
      "production": {
        "country": "FR",
        "share": "MAJ"
      }
    },
    {
      "id": "FR2022_027",
      "slug": "fr2022-027-ps-la-dipsarition",
      "title": {
        "native": "PS : La diPSarition ?"
      },
      "filmType": "D",
      "genre": "DEX",
      "release": {
        "type": "THE",
        "year": 2022
      },
      "tags": "state institutions",
      "production": {
        "country": "FR",
        "share": "MAJ"
      }
    },
    {
      "id": "FR2022_027",
      "slug": "fr2022-027-ps-la-dipsarition",
      "title": {
        "native": "PS : La diPSarition ?"
      },
      "filmType": "D",
      "genre": "DPA",
      "release": {
        "type": "THE",
        "year": 2022
      },
      "tags": "state institutions",
      "production": {
        "country": "FR",
        "share": "MAJ"
      }
    },
    {
      "id": "FR2022_027",
      "slug": "fr2022-027-ps-la-dipsarition",
      "title": {
        "native": "PS : La diPSarition ?"
      },
      "filmType": "D",
      "genre": "DPA",
      "release": {
        "type": "THE",
        "year": 2022
      },
      "tags": "professional politics",
      "production": {
        "country": "FR",
        "share": "MAJ"
      }
    },
    {
      "id": "FR2022_027",
      "slug": "fr2022-027-ps-la-dipsarition",
      "title": {
        "native": "PS : La diPSarition ?"
      },
      "filmType": "D",
      "genre": "DPA",
      "release": {
        "type": "THE",
        "year": 2022
      },
      "tags": "celebrity",
      "production": {
        "country": "FR",
        "share": "MAJ"
      }
    },
    {
      "id": "FR2022_027",
      "slug": "fr2022-027-ps-la-dipsarition",
      "title": {
        "native": "PS : La diPSarition ?"
      },
      "filmType": "D",
      "genre": "DEX",
      "release": {
        "type": "THE",
        "year": 2022
      },
      "tags": "activism",
      "production": {
        "country": "FR",
        "share": "MAJ"
      }
    },
    {
      "id": "FR2022_027",
      "slug": "fr2022-027-ps-la-dipsarition",
      "title": {
        "native": "PS : La diPSarition ?"
      },
      "filmType": "D",
      "genre": "DPA",
      "release": {
        "type": "THE",
        "year": 2022
      },
      "tags": "activism",
      "production": {
        "country": "FR",
        "share": "MAJ"
      }
    },
    {
      "id": "FR2022_027",
      "slug": "fr2022-027-ps-la-dipsarition",
      "title": {
        "native": "PS : La diPSarition ?"
      },
      "filmType": "D",
      "genre": "DEX",
      "release": {
        "type": "THE",
        "year": 2022
      },
      "tags": "celebrity",
      "production": {
        "country": "FR",
        "share": "MAJ"
      }
    }
  ]
}