{
  "id": "Michael Gould",
  "type": "person",
  "slug": "michael-gould",
  "name": "Michael Gould",
  "birthYear": 1961,
  "nationality": "GB",
  "gender": "M",
  "character": [
    {
      "id": "GB2022_076_04",
      "age": "2",
      "gender": "M",
      "origin": "WWE",
      "ability": "AB",
      "assistedMobility": "AB",
      "film": {
        "id": "GB2022_076",
        "slug": "gb2022-076-the-duke",
        "title": {
          "native": "The Duke"
        },
        "filmType": "F",
        "genre": "HIS",
        "release": {
          "type": "THE",
          "year": 2022
        },
        "tags": "mass media",
        "production": {
          "country": "GB",
          "share": "MAJ"
        }
      }
    },
    {
      "id": "GB2021_034_01",
      "age": "2",
      "gender": "M",
      "sexuality": "HE",
      "origin": "WWE",
      "class": "MC",
      "ability": "AB",
      "assistedMobility": "AB",
      "film": {
        "id": "GB2021_034",
        "slug": "gb2021-034-undergods",
        "title": {
          "native": "Undergods"
        },
        "filmType": "F",
        "genre": "DYS",
        "release": {
          "type": "THE",
          "year": 2021
        },
        "tags": "segregation",
        "production": {
          "country": "EE",
          "share": "MIN"
        }
      }
    }
  ]
}