{
  "id":"Nora Agapi",
  "type":"person",
  "slug":"nora-agapi",
  "name":"Nora Agapi",
  "birthYear":1974,
  "deathYear":0,
  "nationality":"RO",
  "gender":"F",
  "character":[

  ],
  "director":[
    {
      "id":"RO2019_019",
      "slug":"ro2019-019-timebox",
      "title":{
        "native":"Timebox",
        "english":"Timebox"
      },
      "filmType":"D",
      "genre":"DPA",
      "release":{
        "type":"THE",
        "year":2019
      },
      "tags":"retirement",
      "production":{
        "country":"RO",
        "share":"MAJ"
      }
    },
    {
      "id":"RO2019_019",
      "slug":"ro2019-019-timebox",
      "title":{
        "native":"Timebox",
        "english":"Timebox"
      },
      "filmType":"D",
      "genre":"DPA",
      "release":{
        "type":"THE",
        "year":2019
      },
      "tags":"precarity",
      "production":{
        "country":"RO",
        "share":"MAJ"
      }
    },
    {
      "id":"RO2019_019",
      "slug":"ro2019-019-timebox",
      "title":{
        "native":"Timebox",
        "english":"Timebox"
      },
      "filmType":"D",
      "genre":"DPA",
      "release":{
        "type":"THE",
        "year":2019
      },
      "tags":"new start",
      "production":{
        "country":"RO",
        "share":"MAJ"
      }
    },
    {
      "id":"RO2019_019",
      "slug":"ro2019-019-timebox",
      "title":{
        "native":"Timebox",
        "english":"Timebox"
      },
      "filmType":"D",
      "genre":"DPA",
      "release":{
        "type":"THE",
        "year":2019
      },
      "tags":"loneliness",
      "production":{
        "country":"RO",
        "share":"MAJ"
      }
    },
    {
      "id":"RO2019_019",
      "slug":"ro2019-019-timebox",
      "title":{
        "native":"Timebox",
        "english":"Timebox"
      },
      "filmType":"D",
      "genre":"DPA",
      "release":{
        "type":"THE",
        "year":2019
      },
      "tags":"fatherhood",
      "production":{
        "country":"RO",
        "share":"MAJ"
      }
    },
    {
      "id":"RO2019_019",
      "slug":"ro2019-019-timebox",
      "title":{
        "native":"Timebox",
        "english":"Timebox"
      },
      "filmType":"D",
      "genre":"DPA",
      "release":{
        "type":"THE",
        "year":2019
      },
      "tags":"independent home",
      "production":{
        "country":"RO",
        "share":"MAJ"
      }
    },
    {
      "id":"RO2019_019",
      "slug":"ro2019-019-timebox",
      "title":{
        "native":"Timebox",
        "english":"Timebox"
      },
      "filmType":"D",
      "genre":"DPA",
      "release":{
        "type":"THE",
        "year":2019
      },
      "tags":"artistic creation",
      "production":{
        "country":"RO",
        "share":"MAJ"
      }
    },
    {
      "id":"RO2019_019",
      "slug":"ro2019-019-timebox",
      "title":{
        "native":"Timebox",
        "english":"Timebox"
      },
      "filmType":"D",
      "genre":"DPA",
      "release":{
        "type":"THE",
        "year":2019
      },
      "tags":"cultural memory",
      "production":{
        "country":"RO",
        "share":"MAJ"
      }
    },
    {
      "id":"RO2019_019",
      "slug":"ro2019-019-timebox",
      "title":{
        "native":"Timebox",
        "english":"Timebox"
      },
      "filmType":"D",
      "genre":"DPA",
      "release":{
        "type":"THE",
        "year":2019
      },
      "tags":"personal memory",
      "production":{
        "country":"RO",
        "share":"MAJ"
      }
    }
  ]
}