{"id":"Daisy Aitkens","type":"Biography","slug":"daisy-aitkens","name":"Daisy Aitkens","birthYear":1986,"nationality":"United Kingdom of Great Britain and Northern Ireland (the)","gender":"Female identifying","director":[{"filmType":"Fiction film","genre":"Comedy","id":"GB2018_036","production":{"country":"United Kingdom of Great Britain and Northern Ireland (the)","share":"Majority coproducer"},"release":{"type":"Theatrical release","year":2018},"slug":"gb2018-036-you-me-and-him","tags":"independent home","title":{"native":"You, Me and Him"}}]}