{"id":"Paolo Virzì","type":"Biography","slug":"paolo-virzi","name":"Paolo Virzì","birthYear":1964,"nationality":"Italy","gender":"Male identifying","director":[{"filmType":"Fiction film","genre":"Road Movie","id":"IT2018_008","production":{"country":"Italy","share":"Majority coproducer"},"release":{"type":"Theatrical release","year":2018},"slug":"it2018-008-the-leisure-seeker","tags":"marriage","title":{"english":"The Leisure Seeker","native":"The Leisure Seeker"}},{"filmType":"Fiction film","genre":"Metacinema","id":"IT2018_024","production":{"country":"Italy","share":"Majority coproducer"},"release":{"type":"Theatrical release","year":2018},"slug":"it2018-024-notti-magiche","tags":"artistic creation","title":{"english":"Magical Nights","native":"Notti magiche"}},{"filmType":"Fiction film","genre":"Disaster Film","id":"IT2022_008","production":{"country":"Italy","share":"Majority coproducer"},"release":{"type":"Theatrical release","year":2022},"slug":"it2022-008-siccita","tags":"new start","title":{"english":"Dry","native":"Siccità"}}]}