{
  "id":"DE2018_038",
  "type":"film",
  "slug":"de2018-038-spielmacher",
  "title":{
    "native":"Spielmacher",
    "english":"Playmaker"
  },
  "filmType":"F",
  "release":{
    "type":"THE",
    "date":1523491200000,
    "year":2018
  },
  "production":{
    "country":"DE",
    "share":"MAJ"
  },
  "media":{
    "trailerUrl":"https:\/\/www.youtube.com\/watch?v=g5GowAfRvv8&ab_channel=palacecinemas",
    "posterUrl":"https:\/\/www.imdb.com\/title\/tt7231560\/mediaviewer\/rm2330019840\/?ref_=tt_ov_i"
  },
  "genre":[
    "DRA",
    "CRI",
    "SPO"
  ],
  "tags":[
    "return home",
    "new start",
    "crime"
  ],
  "director":[
    {
      "id":"Timon Modersohn",
      "name":"Timon Modersohn",
      "birthYear":1978,
      "deathYear":0,
      "gender":"M",
      "nationality":"DE"
    }
  ],
  "character":[

  ],
  "synopsis":{
    "native":"Einst tr\u00e4umte Ivo (Frederick Lau) von einer Karriere als Profifu\u00dfballer, doch mittlerweile ist er vorbestraft und nicht mehr als Fu\u00dfballer aktiv. Dann lernt er jedoch eines Tages den hoffnungsvollen Nachwuchskicker Lukas (Mateo Wansing Lorrio) kennen, dessen gewaltiges Talent er sofort erkennt. Ivo unterst\u00fctzt Lukas fortan mit aller Kraft bei dessen Traum von der Profikarriere, teils weil er Lukas ehrlich sympathisch findet, teil aber auch, um die Entt\u00e4uschung \u00fcber seine eigenen gescheiterten Ambitionen zu verarbeiten. Als er sich dann auch noch in Lukas' Mutter Vera (Antje Traue) verliebt, schein Ivos Gl\u00fcck perfekt. Doch dann wird er von seiner kriminellen Vergangenheit eingeholt, als ihn der charismatische Dejan (Oliver Masucci) in seine illegalen Gesch\u00e4fte hineinzieht und Ivo muss alles riskieren, um Lukas vor demselben Schicksal zu bewahren...",
    "english":"Just released from prison, ex-Footballer Ivo gets tangled up in making his way in the world of rigged sports betting and finding love with the mother of his protege player."
  }
}