{
  "id":"FR2019_117",
  "type":"film",
  "slug":"fr2019-117-yves",
  "title":{
    "native":"Yves",
    "english":"All About Yves"
  },
  "filmType":"F",
  "release":{
    "type":"THE",
    "date":1561507200000,
    "year":2019
  },
  "production":{
    "country":"FR",
    "share":"MAJ"
  },
  "media":{
    "trailerUrl":"https:\/\/www.youtube.com\/watch?v=FFaJWSdDpAQ",
    "posterUrl":"https:\/\/medias.unifrance.org\/medias\/206\/35\/205774\/format_page\/yves.jpg"
  },
  "genre":[
    "COM"
  ],
  "tags":[
    "state institutions",
    "high rank employment"
  ],
  "director":[
    {
      "id":"Beno\u00eet Forgeard",
      "slug":"benoit-forgeard",
      "name":"Beno\u00eet Forgeard",
      "birthYear":1973,
      "deathYear":0,
      "gender":"M",
      "nationality":"FR"
    }
  ],
  "character":[

  ],
  "synopsis":{
    "native":"J\u00e9rem s'installe dans la maison de sa m\u00e9m\u00e9 pour y composer son premier disque. Il y fait la rencontre de So, myst\u00e9rieuse enqu\u00eatrice pour le compte de la start-up Digital Cool. Elle le persuade de prendre \u00e0 l'essai Yves, un r\u00e9frig\u00e9rateur intelligent, cens\u00e9 lui simplifier la vie\u2026",
    "english":"Jerem decides to settle at his grandma\u2019s place to compose his first album. There, he meets So, a mysterious investigator working on behalf of the startup Digital Cool. She will persuade Jerem to try out Yves, a new kind of smart refrigerator gifted with an IA. Little by little, Yves creates bonds of friendship with Jerem and, by becoming his ghost writer, will turn him into a star. With Yves, life was supposed to be easier..."
  }
}