{
  "filmId":"FR2018_014",
  "title":"L'Insulte",
  "titleEn":"The Insult",
  "director":"Ziad Doueiri",
  "releaseType":"THE",
  "releaseDate":1517356800000,
  "type":"F",
  "releaseYear":2018,
  "directorName":"Ziad Doueiri",
  "directorBirthYear":1963,
  "directorDeathYear":0,
  "directorGender":"M",
  "directorNationality":"LB",
  "genre":"DRA",
  "trailerUrl":"https:\/\/www.youtube.com\/watch?v=d2aTniBg7WA",
  "posterUrl":"https:\/\/medias.unifrance.org\/medias\/104\/207\/184168\/format_page\/the-insult.jpg",
  "synopsis":"\u00c0 Beyrouth, de nos jours, une insulte qui d\u00e9g\u00e9n\u00e8re conduit Toni (chr\u00e9tien libanais) et Yasser (r\u00e9fugi\u00e9 palestinien) devant les tribunaux. De blessures secr\u00e8tes en r\u00e9v\u00e9lations, l'affrontement des avocats porte le Liban au bord de l'explosion sociale mais oblige ces deux hommes \u00e0 se regarder en face.",
  "synopsisEn":"In today\u2019s Beirut, an insult blown out of proportions finds Toni, a Lebanese Christian, and Yasser, a Palestinian refugee, in court. From secret wounds to traumatic revelations, the media circus surrounding the case puts Lebanon through a social explosion, forcing Toni and Yasser to reconsider their lives and prejudices.",
  "country":[
    "LB",
    "FR"
  ],
  "productionShare":[
    "MAJ",
    "MIN"
  ],
  "tags":[
    "racial discrimination",
    "migration",
    "state institutions",
    "crime",
    "high rank employment"
  ],
  "charId":"FR2018_014_01",
  "perId":"Kamel El Basha",
  "charAge":"2",
  "charGender":"M",
  "charSexuality":"HE",
  "charOrigin":"MEA",
  "charClass":"MC",
  "charProfession":"EM",
  "charAbility":"AB",
  "assistedMobility":"N",
  "perName":null,
  "perBirthYear":0,
  "perDeathYear":0,
  "perGender":null,
  "perNationality":null,
  "perRole":null,
  "slug":"fr2018-014-l-insulte"
}