{
  "id": "IT2022_045",
  "type": "Film",
  "slug": "it2022-045-sposa-in-rosso",
  "title": {
    "native": "Sposa in rosso",
    "english": "The Bride in Red"
  },
  "filmType": "Fiction film",
  "release": {
    "type": "Theatrical release",
    "date": "2022-04-08",
    "year": 2022
  },
  "production": {
    "country": "Italy",
    "share": "Majority coproducer"
  },
  "media": {
    "trailerUrl": "https://www.youtube.com/watch?v=bGrkZnU1DD4",
    "posterUrl": "https://www.imdb.com/title/tt15517516/mediaviewer/rm3763079169/?ref_=tt_ov_i"
  },
  "genre": [
    "Romance",
    "Comedy"
  ],
  "tags": [
    "parenthood",
    "wedding",
    "extended family"
  ],
  "director": [
    {
      "id": "Gianni Costantino",
      "slug": "gianni-costantino",
      "name": "Gianni Costantino",
      "birthYear": 1971,
      "gender": "Male identifying",
      "nationality": "Italy"
    }
  ],
  "synopsis": {
    "native": "Roberta (Sarah Felberbaum) e Le\u00f2n (Eduardo Noriega), quarantenni precari in cerca di riscatto, inscenano un matrimonio finto in Puglia per intascare i soldi delle buste che gli invitati regalano agli sposi. I complici sono il trasformista Giorgio (Massimo Ghini), amico mentore di Le\u00f2n, e l\u2019anticonformista Giada (Cristina Donadio), zia di Roberta. Gli ostacoli sono i familiari della sposa. La madre asfissiante Lucrezia (Anna Galiena), il fratello paranoico Sauro (Dino Abbrescia) e il padre fuori di testa Alberto (Maurizio Marchetti). In una girandola di imprevisti non sar\u00e0 facile per i protagonisti prendersi la rivincita che meritano. E forse qualcosa di pi\u00f9. Un film avventuroso. Una commedia dei sentimenti. E tra realt\u00e0 e finzione la promessa di una grande storia d\u2019amore.",
    "english": "Roberta and Le\u00f2n are two casual workers in their forties looking to upgrade their precarious lives. Their big idea is to fake a wedding and pocket the many cash-filled envelopes coming left and right from the generous guests. Their partners-in-crime are Le\u00f2n's chameleonic friend and mentor Giorgio and Giada, Roberta's nonconformist aunt. Roberta's family is the one obstacle in their otherwise perfect plan. Lucrezia is a suffocating mother, Sauro is a paranoid brother, and her dad Alberto is, in one word, a lunatic. A whirlwind of events will make it hard for them to take the revenge they feel they deserve. And maybe something more."
  }
}