{
  "id":"IT2023_125",
  "type":"film",
  "slug":"it2023-125-anatar",
  "title":{
    "native":"Anatar",
    "english":""
  },
  "filmType":"F",
  "release":{
    "type":"THE",
    "date":1674086400000,
    "year":2023
  },
  "production":{
    "country":"IT",
    "share":"MAJ"
  },
  "media":{
    "trailerUrl":"https:\/\/www.youtube.com\/watch?v=5_H99T5HJsU",
    "posterUrl":"https:\/\/www.imdb.com\/title\/tt17351870\/mediaviewer\/rm2708080385\/?ref_=tt_ov_i"
  },
  "genre":[
    "SCI",
    "FAN",
    "COM"
  ],
  "tags":[
    "natural"
  ],
  "director":[
    {
      "id":"Alan Smithee",
      "slug":"alan-smithee",
      "name":"Alan Smithee",
      "birthYear":0,
      "deathYear":0,
      "gender":null,
      "nationality":""
    }
  ],
  "character":[

  ],
  "synopsis":{
    "native":"Un popolo spaziale di anatre umanoidi, gli Anatar, \u00e8 alla ricerca di un nuovo pianeta da abitare dopo che il proprio, Anat, ha esaurito tutte le risorse. Il comandante Dark Feather scova il piccolo pianeta di Pandoro e vorrebbe attaccarlo per depredarlo. La principessa Avia, figlia dell'imperatore Quack, decide di assumere sembianze umane per salvare gli umani dalla distruzione.",
    "english":"Alien ducks seek new home after destroying planet. Arrive on Pandoro, harmonious world. Navigate strange environment, experience love, conflict, cultural clashes."
  }
}